LICENSE
MANIFEST.in
README.md
install.json
package.json
pyproject.toml
setup.py
tsconfig.json
yarn.lock
jupyterlab_pachyderm_theme/__init__.py
jupyterlab_pachyderm_theme/_version.py
jupyterlab_pachyderm_theme.egg-info/PKG-INFO
jupyterlab_pachyderm_theme.egg-info/SOURCES.txt
jupyterlab_pachyderm_theme.egg-info/dependency_links.txt
jupyterlab_pachyderm_theme.egg-info/not-zip-safe
jupyterlab_pachyderm_theme.egg-info/requires.txt
jupyterlab_pachyderm_theme.egg-info/top_level.txt
jupyterlab_pachyderm_theme/labextension/build_log.json
jupyterlab_pachyderm_theme/labextension/package.json
jupyterlab_pachyderm_theme/labextension/static/1724159c2bb3bed59ecf7318e0cd2d74.svg
jupyterlab_pachyderm_theme/labextension/static/lib_index_js-webpack_sharing_consume_default_lumino_coreutils-webpack_sharing_consume_default-afeeb2.09df7715ec8f490590ef.js
jupyterlab_pachyderm_theme/labextension/static/lib_index_js-webpack_sharing_consume_default_lumino_coreutils-webpack_sharing_consume_default-afeeb2.09df7715ec8f490590ef.js.map
jupyterlab_pachyderm_theme/labextension/static/remoteEntry.69f9cfe9cc1c5843a203.js
jupyterlab_pachyderm_theme/labextension/static/remoteEntry.69f9cfe9cc1c5843a203.js.map
jupyterlab_pachyderm_theme/labextension/static/style.js
jupyterlab_pachyderm_theme/labextension/static/style_index_js.ef11e936c56895947450.js
jupyterlab_pachyderm_theme/labextension/static/style_index_js.ef11e936c56895947450.js.map
jupyterlab_pachyderm_theme/labextension/static/vendors-node_modules_lumino_polling_dist_index_es6_js.31e2e64f4b60320ca4bc.js
jupyterlab_pachyderm_theme/labextension/static/vendors-node_modules_lumino_polling_dist_index_es6_js.31e2e64f4b60320ca4bc.js.map
src/index.ts
src/svg.d.ts
style/fav_icon.svg
style/index.css
style/index.js
style/pachyderm_logo.svg