Metadata-Version: 2.1
Name: jupyterlab-pachyderm-theme
Version: 0.1.2
Summary: A JupyterLab Pachyderm theme with a splash extension.
Home-page: https://github.com/pachyderm/jupyterlab-pachyderm-theme
Author: Jimmy Whitaker
License: BSD-3-Clause
Keywords: Jupyter,JupyterLab,JupyterLab3
Platform: Linux
Platform: Mac OS X
Platform: Windows
Classifier: License :: OSI Approved :: BSD License
Classifier: Programming Language :: Python
Classifier: Programming Language :: Python :: 3
Classifier: Programming Language :: Python :: 3.6
Classifier: Programming Language :: Python :: 3.7
Classifier: Programming Language :: Python :: 3.8
Classifier: Programming Language :: Python :: 3.9
Classifier: Framework :: Jupyter
Requires-Python: >=3.6
License-File: LICENSE
